[{"loc_item_link":"fsa2000027660/PP","call_number":"LC-USF34-046077","photograph_type":"E","photographer_name":"Jack Delano","caption":"Abandoned house in the Pine Camp Expansion area near Watertown, New York","year":"1941","month":"10","vanderbilt_level1":"The Land","vanderbilt_level2":"Farms, Lands, Conditions","vanderbilt_level3":"Abandoned Farms","lot_number":"1308","city":"Watertown","county":"Jefferson County","state":"New York","country":"United States","longitude":"-75.9107565","latitude":"43.9747838","fips_code":"36045","img_large_path":"fsa/8c29000/8c29100/8c29165v.jpg","img_medium_path":"fsa/8c29000/8c29100/8c29165r.jpg","img_thumb_img":"fsa/8c29000/8c29100/8c29165_150px.jpg"},{"loc_item_link":"fsa2000027663/PP","call_number":"LC-USF34-046079","photograph_type":"E","photographer_name":"Jack Delano","caption":"Mr. Ray Lyman FSA (Farm Security Administration) dairy farmer near Castleton, Vermont","year":"1941","month":"8","vanderbilt_level1":"People As Such","vanderbilt_level2":"Groups and Individuals","vanderbilt_level3":"Farmers and Farmers' Heads","lot_number":"1235","city":"Castleton","county":"Rutland County","state":"Vermont","country":"United States","longitude":"-73.179832","latitude":"43.6106224","fips_code":"50021","img_large_path":"fsa/8c29000/8c29100/8c29166v.jpg","img_medium_path":"fsa/8c29000/8c29100/8c29166r.jpg","img_thumb_img":"fsa/8c29000/8c29100/8c29166_150px.jpg"},{"loc_item_link":"fsa2000027665/PP","call_number":"LC-USF342-T01-046081","photograph_type":"A","photographer_name":"Jack Delano","caption":"Dairy barn near Sheldon Springs, Vermont","year":"1941","month":"8","vanderbilt_level1":"The Land","vanderbilt_level2":"Farms, Lands, Conditions","vanderbilt_level3":"Barns","lot_number":"1245","city":"Sheldon Springs","county":"Franklin County","state":"Vermont","country":"United States","longitude":"-72.9776335","latitude":"44.9061559","fips_code":"50011","img_large_path":"fsa/8c52000/8c52800/8c52835v.jpg","img_medium_path":"fsa/8c52000/8c52800/8c52835r.jpg","img_thumb_img":"fsa/8c52000/8c52800/8c52835_150px.jpg"},{"loc_item_link":"fsa2000027666/PP","call_number":"LC-USF342-T-046082","photograph_type":"A","photographer_name":"Jack Delano","caption":"Hay stacks in a field near Essex Junction, Vermont","year":"1941","month":"8","vanderbilt_level1":"","vanderbilt_level2":"","vanderbilt_level3":"","lot_number":"1245","city":"Essex Junction","county":"Chittenden County","state":"Vermont","country":"United States","longitude":"-73.1109604","latitude":"44.4906054","fips_code":"50007","img_large_path":"fsa/8c52000/8c52800/8c52836v.jpg","img_medium_path":"fsa/8c52000/8c52800/8c52836r.jpg","img_thumb_img":"fsa/8c52000/8c52800/8c52836_150px.jpg"},{"loc_item_link":"fsa2000027667/PP","call_number":"LC-USF342-T-046083","photograph_type":"A","photographer_name":"Jack Delano","caption":"General store and gas station in Hinesburg, Vermont","year":"1941","month":"8","vanderbilt_level1":"","vanderbilt_level2":"","vanderbilt_level3":"","lot_number":"1243","city":"Hinesburg","county":"Chittenden County","state":"Vermont","country":"United States","longitude":"-73.110679","latitude":"44.3292199","fips_code":"50007","img_large_path":"","img_medium_path":"","img_thumb_img":""},{"loc_item_link":"fsa2000027669/PP","call_number":"LC-USF342-T-046085","photograph_type":"A","photographer_name":"Jack Delano","caption":"General view of the town of Mount Holly, Vermont","year":"1941","month":"8","vanderbilt_level1":"The Land","vanderbilt_level2":"Mountains, Deserts, Foothills, Plains","vanderbilt_level3":"Mountains","lot_number":"1245","city":"Mount Holly","county":"Rutland County","state":"Vermont","country":"United States","longitude":"-72.8248225","latitude":"43.4522932","fips_code":"50021","img_large_path":"fsa/8c52000/8c52800/8c52839v.jpg","img_medium_path":"fsa/8c52000/8c52800/8c52839r.jpg","img_thumb_img":"fsa/8c52000/8c52800/8c52839_150px.jpg"},{"loc_item_link":"fsa2000027671/PP","call_number":"LC-USF342-T-046087","photograph_type":"A","photographer_name":"Jack Delano","caption":"The children of Mr. Ray Lyman, FSA (Farm Security Administration) dairy farmer near Castleton, Vermont","year":"1941","month":"8","vanderbilt_level1":"People As Such","vanderbilt_level2":"Children","vanderbilt_level3":"In the Country","lot_number":"1235","city":"Castleton","county":"Rutland County","state":"Vermont","country":"United States","longitude":"-73.179832","latitude":"43.6106224","fips_code":"50021","img_large_path":"fsa/8c52000/8c52800/8c52841v.jpg","img_medium_path":"fsa/8c52000/8c52800/8c52841r.jpg","img_thumb_img":"fsa/8c52000/8c52800/8c52841_150px.jpg"},{"loc_item_link":"fsa2000027673/PP","call_number":"LC-USF342-T-046089","photograph_type":"A","photographer_name":"Jack Delano","caption":"Two children of Mr. Ray Lyman, FSA (Farm Security Administration) dairy farmer near Castleton, Vermont","year":"1941","month":"8","vanderbilt_level1":"People As Such","vanderbilt_level2":"Children","vanderbilt_level3":"Older Boys","lot_number":"1235","city":"Castleton","county":"Rutland County","state":"Vermont","country":"United States","longitude":"-73.179832","latitude":"43.6106224","fips_code":"50021","img_large_path":"fsa/8c52000/8c52800/8c52843v.jpg","img_medium_path":"fsa/8c52000/8c52800/8c52843r.jpg","img_thumb_img":"fsa/8c52000/8c52800/8c52843_150px.jpg"},{"loc_item_link":"fsa2000027674/PP","call_number":"LC-USF34-046090","photograph_type":"D","photographer_name":"Jack Delano","caption":"Railroad car and wood pile at the Missisquoi Corporation paper mill in Sheldon Springs, Vermont","year":"1941","month":"9","vanderbilt_level1":"Work","vanderbilt_level2":"Processing and Manufacturing","vanderbilt_level3":"Papennills and Paper Products","lot_number":"1247","city":"Sheldon Springs","county":"Franklin County","state":"Vermont","country":"United States","longitude":"-72.9776335","latitude":"44.9061559","fips_code":"50011","img_large_path":"fsa/8c07000/8c07200/8c07268v.jpg","img_medium_path":"fsa/8c07000/8c07200/8c07268r.jpg","img_thumb_img":"fsa/8c07000/8c07200/8c07268_150px.jpg"},{"loc_item_link":"fsa2000027675/PP","call_number":"LC-USF34-046091","photograph_type":"D","photographer_name":"Jack Delano","caption":"Testing the pulp at the Mississquoi Corporation paper mill in Sheldon Springs, Vermont","year":"1941","month":"9","vanderbilt_level1":"Work","vanderbilt_level2":"Processing and Manufacturing","vanderbilt_level3":"Papennills and Paper Products","lot_number":"1247","city":"Sheldon Springs","county":"Franklin County","state":"Vermont","country":"United States","longitude":"-72.9776335","latitude":"44.9061559","fips_code":"50011","img_large_path":"fsa/8c07000/8c07200/8c07269v.jpg","img_medium_path":"fsa/8c07000/8c07200/8c07269r.jpg","img_thumb_img":"fsa/8c07000/8c07200/8c07269_150px.jpg"},{"loc_item_link":"fsa2000027677/PP","call_number":"LC-USF34-046093","photograph_type":"D","photographer_name":"Jack Delano","caption":"Paper pulp at the Mississquoi Corporation paper mill in Sheldon Springs, Vermont","year":"1941","month":"9","vanderbilt_level1":"Work","vanderbilt_level2":"Processing and Manufacturing","vanderbilt_level3":"Papennills and Paper Products","lot_number":"1247","city":"Sheldon Springs","county":"Franklin County","state":"Vermont","country":"United States","longitude":"-72.9776335","latitude":"44.9061559","fips_code":"50011","img_large_path":"fsa/8c07000/8c07200/8c07271v.jpg","img_medium_path":"fsa/8c07000/8c07200/8c07271r.jpg","img_thumb_img":"fsa/8c07000/8c07200/8c07271_150px.jpg"},{"loc_item_link":"fsa2000027679/PP","call_number":"LC-USF34-046095","photograph_type":"D","photographer_name":"Jack Delano","caption":"Paper pulp being rolled out at the Mississquoi Corporation paper mill in Sheldon Springs, Vermont","year":"1941","month":"9","vanderbilt_level1":"Work","vanderbilt_level2":"Processing and Manufacturing","vanderbilt_level3":"Papennills and Paper Products","lot_number":"1247","city":"Sheldon Springs","county":"Franklin County","state":"Vermont","country":"United States","longitude":"-72.9776335","latitude":"44.9061559","fips_code":"50011","img_large_path":"fsa/8c07000/8c07200/8c07273v.jpg","img_medium_path":"fsa/8c07000/8c07200/8c07273r.jpg","img_thumb_img":"fsa/8c07000/8c07200/8c07273_150px.jpg"},{"loc_item_link":"fsa2000027680/PP","call_number":"LC-USF34-046096","photograph_type":"D","photographer_name":"Jack Delano","caption":"Vat in which paper pulp is churned at the Mississquoi Corporation paper mill in Sheldon Springs, Vermont","year":"1941","month":"9","vanderbilt_level1":"Work","vanderbilt_level2":"Processing and Manufacturing","vanderbilt_level3":"Papennills and Paper Products","lot_number":"1247","city":"Sheldon Springs","county":"Franklin County","state":"Vermont","country":"United States","longitude":"-72.9776335","latitude":"44.9061559","fips_code":"50011","img_large_path":"fsa/8c07000/8c07200/8c07274v.jpg","img_medium_path":"fsa/8c07000/8c07200/8c07274r.jpg","img_thumb_img":"fsa/8c07000/8c07200/8c07274_150px.jpg"},{"loc_item_link":"fsa2000027681/PP","call_number":"LC-USF34-046097","photograph_type":"D","photographer_name":"Jack Delano","caption":"The wood pile outside the Mississquoi Corporation paper mill in Seldon Springs, Vermont","year":"1941","month":"9","vanderbilt_level1":"Work","vanderbilt_level2":"Processing and Manufacturing","vanderbilt_level3":"Papennills and Paper Products","lot_number":"1247","city":"Sheldon Springs","county":"Franklin County","state":"Vermont","country":"United States","longitude":"-72.9776335","latitude":"44.9061559","fips_code":"50011","img_large_path":"fsa/8c07000/8c07200/8c07275v.jpg","img_medium_path":"fsa/8c07000/8c07200/8c07275r.jpg","img_thumb_img":"fsa/8c07000/8c07200/8c07275_150px.jpg"},{"loc_item_link":"fsa2000027684/PP","call_number":"LC-USF34-046100","photograph_type":"D","photographer_name":"Jack Delano","caption":"One of the machines that grinds wood into pulp at the Mississiquoi Corporation paper mill in Seldon Springs, Vermont","year":"1941","month":"9","vanderbilt_level1":"Work","vanderbilt_level2":"Processing and Manufacturing","vanderbilt_level3":"Papennills and Paper Products","lot_number":"1247","city":"Sheldon Springs","county":"Franklin County","state":"Vermont","country":"United States","longitude":"-72.9776335","latitude":"44.9061559","fips_code":"50011","img_large_path":"fsa/8c07000/8c07200/8c07278v.jpg","img_medium_path":"fsa/8c07000/8c07200/8c07278r.jpg","img_thumb_img":"fsa/8c07000/8c07200/8c07278_150px.jpg"},{"loc_item_link":"fsa2000027685/PP","call_number":"LC-USF34-046101","photograph_type":"D","photographer_name":"Jack Delano","caption":"Pulling paper pulp off the rollers at the Mississquoi Corporation paper mill in Seldon Springs, Vermont","year":"1941","month":"9","vanderbilt_level1":"Work","vanderbilt_level2":"Processing and Manufacturing","vanderbilt_level3":"Chemical Industry","lot_number":"1247","city":"Sheldon Springs","county":"Franklin County","state":"Vermont","country":"United States","longitude":"-72.9776335","latitude":"44.9061559","fips_code":"50011","img_large_path":"fsa/8c07000/8c07200/8c07279v.jpg","img_medium_path":"fsa/8c07000/8c07200/8c07279r.jpg","img_thumb_img":"fsa/8c07000/8c07200/8c07279_150px.jpg"},{"loc_item_link":"fsa2000027687/PP","call_number":"LC-USF34-046103","photograph_type":"D","photographer_name":"Jack Delano","caption":"One of the machines that grinds wood into pulp at the Mississquoi Corporation paper mill. Seldon Springs, Vermont","year":"1941","month":"9","vanderbilt_level1":"Work","vanderbilt_level2":"Processing and Manufacturing","vanderbilt_level3":"Papennills and Paper Products","lot_number":"1247","city":"Sheldon Springs","county":"Franklin County","state":"Vermont","country":"United States","longitude":"-72.9776335","latitude":"44.9061559","fips_code":"50011","img_large_path":"fsa/8c07000/8c07200/8c07281v.jpg","img_medium_path":"fsa/8c07000/8c07200/8c07281r.jpg","img_thumb_img":"fsa/8c07000/8c07200/8c07281_150px.jpg"},{"loc_item_link":"fsa2000027688/PP","call_number":"LC-USF34-046104","photograph_type":"D","photographer_name":"Jack Delano","caption":"Putting paper pulp into vats which further churn the pulp at the Mississquoi Corporation paper mill in Seldon Springs, Vermont","year":"1941","month":"9","vanderbilt_level1":"Work","vanderbilt_level2":"Processing and Manufacturing","vanderbilt_level3":"Papennills and Paper Products","lot_number":"1247","city":"Sheldon Springs","county":"Franklin County","state":"Vermont","country":"United States","longitude":"-72.9776335","latitude":"44.9061559","fips_code":"50011","img_large_path":"fsa/8c07000/8c07200/8c07282v.jpg","img_medium_path":"fsa/8c07000/8c07200/8c07282r.jpg","img_thumb_img":"fsa/8c07000/8c07200/8c07282_150px.jpg"},{"loc_item_link":"fsa2000027690/PP","call_number":"LC-USF34-046106","photograph_type":"D","photographer_name":"Jack Delano","caption":"Wood pile outside the Mississquoi Corporation paper mill in Seldon Springs, Vermont","year":"1941","month":"9","vanderbilt_level1":"Work","vanderbilt_level2":"Processing and Manufacturing","vanderbilt_level3":"Papennills and Paper Products","lot_number":"1247","city":"Sheldon Springs","county":"Franklin County","state":"Vermont","country":"United States","longitude":"-72.9776335","latitude":"44.9061559","fips_code":"50011","img_large_path":"fsa/8c07000/8c07200/8c07284v.jpg","img_medium_path":"fsa/8c07000/8c07200/8c07284r.jpg","img_thumb_img":"fsa/8c07000/8c07200/8c07284_150px.jpg"},{"loc_item_link":"fsa2000027692/PP","call_number":"LC-USF34-046108","photograph_type":"D","photographer_name":"Jack Delano","caption":"One of the machines that grinds wood into pulp at the Mississquoi Corporation paper mill in Seldon Springs, Vermont","year":"1941","month":"9","vanderbilt_level1":"Work","vanderbilt_level2":"Processing and Manufacturing","vanderbilt_level3":"Papennills and Paper Products","lot_number":"1247","city":"Sheldon Springs","county":"Franklin County","state":"Vermont","country":"United States","longitude":"-72.9776335","latitude":"44.9061559","fips_code":"50011","img_large_path":"fsa/8c07000/8c07200/8c07286v.jpg","img_medium_path":"fsa/8c07000/8c07200/8c07286r.jpg","img_thumb_img":"fsa/8c07000/8c07200/8c07286_150px.jpg"},{"loc_item_link":"fsa2000027693/PP","call_number":"LC-USF34-046109","photograph_type":"D","photographer_name":"Jack Delano","caption":"One of the machines that grinds wood into pulp at the Mississquoi Corporation paper mill at Sheldon Springs, Vermont","year":"1941","month":"9","vanderbilt_level1":"Work","vanderbilt_level2":"Processing and Manufacturing","vanderbilt_level3":"Papennills and Paper Products","lot_number":"1247","city":"Sheldon Springs","county":"Franklin County","state":"Vermont","country":"United States","longitude":"-72.9776335","latitude":"44.9061559","fips_code":"50011","img_large_path":"fsa/8c07000/8c07200/8c07287v.jpg","img_medium_path":"fsa/8c07000/8c07200/8c07287r.jpg","img_thumb_img":"fsa/8c07000/8c07200/8c07287_150px.jpg"},{"loc_item_link":"fsa2000027694/PP","call_number":"LC-USF34-046110","photograph_type":"D","photographer_name":"Jack Delano","caption":"One of the last stages in making paper at the Mississquoi Corporation paper mill in Sheldon Springs, Vermont","year":"1941","month":"9","vanderbilt_level1":"Work","vanderbilt_level2":"Processing and Manufacturing","vanderbilt_level3":"Papennills and Paper Products","lot_number":"1247","city":"Sheldon Springs","county":"Franklin County","state":"Vermont","country":"United States","longitude":"-72.9776335","latitude":"44.9061559","fips_code":"50011","img_large_path":"fsa/8c07000/8c07200/8c07288v.jpg","img_medium_path":"fsa/8c07000/8c07200/8c07288r.jpg","img_thumb_img":"fsa/8c07000/8c07200/8c07288_150px.jpg"},{"loc_item_link":"fsa2000027695/PP","call_number":"LC-USF34-046111","photograph_type":"D","photographer_name":"Jack Delano","caption":"Section of a large rolling paper machine at the Mississquoi Corporation paper mill. Sheldon Springs, Vermont","year":"1941","month":"9","vanderbilt_level1":"Work","vanderbilt_level2":"Processing and Manufacturing","vanderbilt_level3":"Papennills and Paper Products","lot_number":"1247","city":"Sheldon Springs","county":"Franklin County","state":"Vermont","country":"United States","longitude":"-72.9776335","latitude":"44.9061559","fips_code":"50011","img_large_path":"fsa/8c07000/8c07200/8c07289v.jpg","img_medium_path":"fsa/8c07000/8c07200/8c07289r.jpg","img_thumb_img":"fsa/8c07000/8c07200/8c07289_150px.jpg"},{"loc_item_link":"fsa2000027696/PP","call_number":"LC-USF34-046112","photograph_type":"D","photographer_name":"Jack Delano","caption":"Sheldon Springs, Vermont paper as it comes off the rollers at the Mississquoi Corporation paper mill","year":"1941","month":"9","vanderbilt_level1":"Work","vanderbilt_level2":"Processing and Manufacturing","vanderbilt_level3":"Papennills and Paper Products","lot_number":"1247","city":"Sheldon Springs","county":"Franklin County","state":"Vermont","country":"United States","longitude":"-72.9776335","latitude":"44.9061559","fips_code":"50011","img_large_path":"fsa/8c07000/8c07200/8c07290v.jpg","img_medium_path":"fsa/8c07000/8c07200/8c07290r.jpg","img_thumb_img":"fsa/8c07000/8c07200/8c07290_150px.jpg"},{"loc_item_link":"fsa2000027697/PP","call_number":"LC-USF34-046113","photograph_type":"D","photographer_name":"Jack Delano","caption":"Trimming paper at the Mississquoi Corporation paper mill in Sheldon Springs, Vermont","year":"1941","month":"9","vanderbilt_level1":"Work","vanderbilt_level2":"Processing and Manufacturing","vanderbilt_level3":"Papennills and Paper Products","lot_number":"1247","city":"Sheldon Springs","county":"Franklin County","state":"Vermont","country":"United States","longitude":"-72.9776335","latitude":"44.9061559","fips_code":"50011","img_large_path":"fsa/8c07000/8c07200/8c07291v.jpg","img_medium_path":"fsa/8c07000/8c07200/8c07291r.jpg","img_thumb_img":"fsa/8c07000/8c07200/8c07291_150px.jpg"},{"loc_item_link":"fsa2000027699/PP","call_number":"LC-USF34-046115","photograph_type":"D","photographer_name":"Jack Delano","caption":"The blacksmith shop in Mississquoi Corporation paper mill in Sheldon Springs, Vermont","year":"1941","month":"9","vanderbilt_level1":"","vanderbilt_level2":"","vanderbilt_level3":"","lot_number":"1247","city":"Sheldon Springs","county":"Franklin County","state":"Vermont","country":"United States","longitude":"-72.9776335","latitude":"44.9061559","fips_code":"50011","img_large_path":"fsa/8c07000/8c07200/8c07293v.jpg","img_medium_path":"fsa/8c07000/8c07200/8c07293r.jpg","img_thumb_img":"fsa/8c07000/8c07200/8c07293_150px.jpg"},{"loc_item_link":"fsa2000027700/PP","call_number":"LC-USF34-046116","photograph_type":"D","photographer_name":"Jack Delano","caption":"Paper pulp being churned in a large vat at the Mississquoi Corporation paper mill at Sheldon Springs, Vermont","year":"1941","month":"9","vanderbilt_level1":"Work","vanderbilt_level2":"Processing and Manufacturing","vanderbilt_level3":"Papennills and Paper Products","lot_number":"1247","city":"Sheldon Springs","county":"Franklin County","state":"Vermont","country":"United States","longitude":"-72.9776335","latitude":"44.9061559","fips_code":"50011","img_large_path":"fsa/8c07000/8c07200/8c07294v.jpg","img_medium_path":"fsa/8c07000/8c07200/8c07294r.jpg","img_thumb_img":"fsa/8c07000/8c07200/8c07294_150px.jpg"},{"loc_item_link":"fsa2000027701/PP","call_number":"LC-USF34-046117","photograph_type":"D","photographer_name":"Jack Delano","caption":"Section of a large rolling machine at the Mississquoi Corporation paper mill in Sheldon Springs, Vermont","year":"1941","month":"9","vanderbilt_level1":"Work","vanderbilt_level2":"Processing and Manufacturing","vanderbilt_level3":"Papennills and Paper Products","lot_number":"1247","city":"Sheldon Springs","county":"Franklin County","state":"Vermont","country":"United States","longitude":"-72.9776335","latitude":"44.9061559","fips_code":"50011","img_large_path":"fsa/8c07000/8c07200/8c07295v.jpg","img_medium_path":"fsa/8c07000/8c07200/8c07295r.jpg","img_thumb_img":"fsa/8c07000/8c07200/8c07295_150px.jpg"},{"loc_item_link":"fsa2000027702/PP","call_number":"LC-USF34-046118","photograph_type":"D","photographer_name":"Jack Delano","caption":"Starting a new roll of paper at the receiving end of the large rolling machine. At the Mississquoi Corporation paper mill. Sheldon Springs, Vermont","year":"1941","month":"9","vanderbilt_level1":"Work","vanderbilt_level2":"Processing and Manufacturing","vanderbilt_level3":"Papennills and Paper Products","lot_number":"1247","city":"Sheldon Springs","county":"Franklin County","state":"Vermont","country":"United States","longitude":"-72.9776335","latitude":"44.9061559","fips_code":"50011","img_large_path":"fsa/8c07000/8c07200/8c07296v.jpg","img_medium_path":"fsa/8c07000/8c07200/8c07296r.jpg","img_thumb_img":"fsa/8c07000/8c07200/8c07296_150px.jpg"},{"loc_item_link":"fsa2000027703/PP","call_number":"LC-USF34-046119","photograph_type":"D","photographer_name":"Jack Delano","caption":"Paper wrapped up and ready for shipping at the Mississquoi Corporation paper mill. Sheldon Springs, Vermont","year":"1941","month":"9","vanderbilt_level1":"Work","vanderbilt_level2":"Processing and Manufacturing","vanderbilt_level3":"Papennills and Paper Products","lot_number":"1247","city":"Sheldon Springs","county":"Franklin County","state":"Vermont","country":"United States","longitude":"-72.9776335","latitude":"44.9061559","fips_code":"50011","img_large_path":"fsa/8c07000/8c07200/8c07297v.jpg","img_medium_path":"fsa/8c07000/8c07200/8c07297r.jpg","img_thumb_img":"fsa/8c07000/8c07200/8c07297_150px.jpg"}]