[{"loc_item_link":"owi2001026329/PP","call_number":"LC-USW3-025196","photograph_type":"D","photographer_name":"John Vachon","caption":"San Augustine, Texas. A man going to the livestock auction","year":"1943","month":"4","vanderbilt_level1":"Cities and Towns","vanderbilt_level2":"Towns and Small Cities","vanderbilt_level3":"Streets","lot_number":"688","city":"San Augustine","county":"San Augustine County","state":"Texas","country":"United States","longitude":"-94.1060282","latitude":"31.5299029","fips_code":"48015","img_large_path":"fsa/8d17000/8d17600/8d17669v.jpg","img_medium_path":"fsa/8d17000/8d17600/8d17669r.jpg","img_thumb_img":"fsa/8d17000/8d17600/8d17669_150px.jpg"},{"loc_item_link":"owi2001026330/PP","call_number":"LC-USW3-025197","photograph_type":"D","photographer_name":"John Vachon","caption":"San Augustine, Texas. A man going to the livestock auction","year":"1943","month":"4","vanderbilt_level1":"Cities and Towns","vanderbilt_level2":"Towns and Small Cities","vanderbilt_level3":"Streets","lot_number":"688","city":"San Augustine","county":"San Augustine County","state":"Texas","country":"United States","longitude":"-94.1060282","latitude":"31.5299029","fips_code":"48015","img_large_path":"fsa/8d17000/8d17600/8d17670v.jpg","img_medium_path":"fsa/8d17000/8d17600/8d17670r.jpg","img_thumb_img":"fsa/8d17000/8d17600/8d17670_150px.jpg"},{"loc_item_link":"owi2001026332/PP","call_number":"LC-USW3-025199","photograph_type":"D","photographer_name":"John Vachon","caption":"San Augustine, Texas. The high school student body singing at a general assembly","year":"1943","month":"4","vanderbilt_level1":"People As Such","vanderbilt_level2":"Children","vanderbilt_level3":"Assemblies, Ceremonies","lot_number":"688","city":"San Augustine","county":"San Augustine County","state":"Texas","country":"United States","longitude":"-94.1060282","latitude":"31.5299029","fips_code":"48015","img_large_path":"fsa/8d17000/8d17600/8d17672v.jpg","img_medium_path":"fsa/8d17000/8d17600/8d17672r.jpg","img_thumb_img":"fsa/8d17000/8d17600/8d17672_150px.jpg"},{"loc_item_link":"owi2001026333/PP","call_number":"LC-USW3-025200","photograph_type":"D","photographer_name":"John Vachon","caption":"San Augustine, Texas. A high school student body singing at a general assembly","year":"1943","month":"4","vanderbilt_level1":"People As Such","vanderbilt_level2":"Children","vanderbilt_level3":"Assemblies, Ceremonies","lot_number":"688","city":"San Augustine","county":"San Augustine County","state":"Texas","country":"United States","longitude":"-94.1060282","latitude":"31.5299029","fips_code":"48015","img_large_path":"fsa/8d17000/8d17600/8d17673v.jpg","img_medium_path":"fsa/8d17000/8d17600/8d17673r.jpg","img_thumb_img":"fsa/8d17000/8d17600/8d17673_150px.jpg"},{"loc_item_link":"owi2001026337/PP","call_number":"LC-USW3-025204","photograph_type":"D","photographer_name":"John Vachon","caption":"San Augustine, Texas. A high school student body singing at a general assembly","year":"1943","month":"4","vanderbilt_level1":"People As Such","vanderbilt_level2":"Children","vanderbilt_level3":"Assemblies, Ceremonies","lot_number":"688","city":"San Augustine","county":"San Augustine County","state":"Texas","country":"United States","longitude":"-94.1060282","latitude":"31.5299029","fips_code":"48015","img_large_path":"fsa/8d17000/8d17600/8d17677v.jpg","img_medium_path":"fsa/8d17000/8d17600/8d17677r.jpg","img_thumb_img":"fsa/8d17000/8d17600/8d17677_150px.jpg"},{"loc_item_link":"owi2001026338/PP","call_number":"LC-USW3-025205","photograph_type":"D","photographer_name":"John Vachon","caption":"San Augustine, Texas. Harlan Hayes with his father, W.F. Hayes, editor of the San Augustine Tribune","year":"1943","month":"4","vanderbilt_level1":"Itellectual and Creative Activity","vanderbilt_level2":"General","vanderbilt_level3":"Newspapers","lot_number":"688","city":"San Augustine","county":"San Augustine County","state":"Texas","country":"United States","longitude":"-94.1060282","latitude":"31.5299029","fips_code":"48015","img_large_path":"fsa/8d17000/8d17600/8d17678v.jpg","img_medium_path":"fsa/8d17000/8d17600/8d17678r.jpg","img_thumb_img":"fsa/8d17000/8d17600/8d17678_150px.jpg"},{"loc_item_link":"owi2001026340/PP","call_number":"LC-USW3-025207","photograph_type":"D","photographer_name":"John Vachon","caption":"San Augustine, Texas. Dr. Rulfs in his office","year":"1943","month":"4","vanderbilt_level1":"Medicine and Health","vanderbilt_level2":"General","vanderbilt_level3":"Physicians","lot_number":"688","city":"San Augustine","county":"San Augustine County","state":"Texas","country":"United States","longitude":"-94.1060282","latitude":"31.5299029","fips_code":"48015","img_large_path":"fsa/8d17000/8d17600/8d17680v.jpg","img_medium_path":"fsa/8d17000/8d17600/8d17680r.jpg","img_thumb_img":"fsa/8d17000/8d17600/8d17680_150px.jpg"},{"loc_item_link":"owi2001026342/PP","call_number":"LC-USW3-025209","photograph_type":"D","photographer_name":"John Vachon","caption":"San Augustine, Texas. A bull for sale at the livestock auction","year":"1943","month":"4","vanderbilt_level1":"Work","vanderbilt_level2":"Selling and Distribution","vanderbilt_level3":"Auctions","lot_number":"688","city":"San Augustine","county":"San Augustine County","state":"Texas","country":"United States","longitude":"-94.1060282","latitude":"31.5299029","fips_code":"48015","img_large_path":"fsa/8d17000/8d17600/8d17682v.jpg","img_medium_path":"fsa/8d17000/8d17600/8d17682r.jpg","img_thumb_img":"fsa/8d17000/8d17600/8d17682_150px.jpg"},{"loc_item_link":"owi2001026344/PP","call_number":"LC-USW3-025211","photograph_type":"D","photographer_name":"John Vachon","caption":"San Augustine, Texas. Lawyer Ramsey in his office","year":"1943","month":"4","vanderbilt_level1":"Organized Society","vanderbilt_level2":"Government","vanderbilt_level3":"Lawyers","lot_number":"688","city":"San Augustine","county":"San Augustine County","state":"Texas","country":"United States","longitude":"-94.1060282","latitude":"31.5299029","fips_code":"48015","img_large_path":"fsa/8d17000/8d17600/8d17684v.jpg","img_medium_path":"fsa/8d17000/8d17600/8d17684r.jpg","img_thumb_img":"fsa/8d17000/8d17600/8d17684_150px.jpg"},{"loc_item_link":"owi2001026345/PP","call_number":"LC-USW3-025212","photograph_type":"D","photographer_name":"John Vachon","caption":"San Augustine, Texas. Sitting on a bench in the courthouse square on Saturday afternoon","year":"1943","month":"4","vanderbilt_level1":"","vanderbilt_level2":"","vanderbilt_level3":"","lot_number":"688","city":"San Augustine","county":"San Augustine County","state":"Texas","country":"United States","longitude":"-94.1060282","latitude":"31.5299029","fips_code":"48015","img_large_path":"fsa/8d17000/8d17600/8d17685v.jpg","img_medium_path":"fsa/8d17000/8d17600/8d17685r.jpg","img_thumb_img":"fsa/8d17000/8d17600/8d17685_150px.jpg"},{"loc_item_link":"owi2001026346/PP","call_number":"LC-USW3-025213","photograph_type":"D","photographer_name":"John Vachon","caption":"San Augustine, Texas. Sitting on a bench in the courthouse square on Saturday afternoon","year":"1943","month":"4","vanderbilt_level1":"People As Such","vanderbilt_level2":"Groups and Individuals","vanderbilt_level3":"In the Streets","lot_number":"NA","city":"San Augustine","county":"San Augustine County","state":"Texas","country":"United States","longitude":"-94.1060282","latitude":"31.5299029","fips_code":"48015","img_large_path":"fsa/8d17000/8d17600/8d17686v.jpg","img_medium_path":"fsa/8d17000/8d17600/8d17686r.jpg","img_thumb_img":"fsa/8d17000/8d17600/8d17686_150px.jpg"},{"loc_item_link":"owi2001026347/PP","call_number":"LC-USW3-025214","photograph_type":"D","photographer_name":"John Vachon","caption":"San Augustine, Texas. Old men sitting on a bench in courthouse square on Saturday afternoon","year":"1943","month":"4","vanderbilt_level1":"People As Such","vanderbilt_level2":"Groups and Individuals","vanderbilt_level3":"Old Men","lot_number":"688","city":"San Augustine","county":"San Augustine County","state":"Texas","country":"United States","longitude":"-94.1060282","latitude":"31.5299029","fips_code":"48015","img_large_path":"fsa/8d17000/8d17600/8d17687v.jpg","img_medium_path":"fsa/8d17000/8d17600/8d17687r.jpg","img_thumb_img":"fsa/8d17000/8d17600/8d17687_150px.jpg"},{"loc_item_link":"owi2001026348/PP","call_number":"LC-USW3-025215","photograph_type":"D","photographer_name":"John Vachon","caption":"San Augustine, Texas. Buildings on the main street which were damaged by the March tornado","year":"1943","month":"4","vanderbilt_level1":"The Land","vanderbilt_level2":"Weather, Floods, Waterways","vanderbilt_level3":"Hurricanes","lot_number":"688","city":"San Augustine","county":"San Augustine County","state":"Texas","country":"United States","longitude":"-94.1060282","latitude":"31.5299029","fips_code":"48015","img_large_path":"fsa/8d17000/8d17600/8d17688v.jpg","img_medium_path":"fsa/8d17000/8d17600/8d17688r.jpg","img_thumb_img":"fsa/8d17000/8d17600/8d17688_150px.jpg"},{"loc_item_link":"owi2001026349/PP","call_number":"LC-USW3-025216","photograph_type":"D","photographer_name":"John Vachon","caption":"San Augustine, Texas. Waiting for the opening of the regular Monday livestock auction","year":"1943","month":"4","vanderbilt_level1":"People As Such","vanderbilt_level2":"Groups and Individuals","vanderbilt_level3":"At Meetings, Events","lot_number":"688","city":"San Augustine","county":"San Augustine County","state":"Texas","country":"United States","longitude":"-94.1060282","latitude":"31.5299029","fips_code":"48015","img_large_path":"fsa/8d17000/8d17600/8d17689v.jpg","img_medium_path":"fsa/8d17000/8d17600/8d17689r.jpg","img_thumb_img":"fsa/8d17000/8d17600/8d17689_150px.jpg"},{"loc_item_link":"owi2001026350/PP","call_number":"LC-USW3-025217","photograph_type":"D","photographer_name":"John Vachon","caption":"San Augustine, Texas. Sheriff Halberd talking with a prisoner in the county jail","year":"1943","month":"4","vanderbilt_level1":"Organized Society","vanderbilt_level2":"Government","vanderbilt_level3":"Law","lot_number":"688","city":"San Augustine","county":"San Augustine County","state":"Texas","country":"United States","longitude":"-94.1060282","latitude":"31.5299029","fips_code":"48015","img_large_path":"fsa/8d17000/8d17600/8d17690v.jpg","img_medium_path":"fsa/8d17000/8d17600/8d17690r.jpg","img_thumb_img":"fsa/8d17000/8d17600/8d17690_150px.jpg"},{"loc_item_link":"owi2001026351/PP","call_number":"LC-USW3-025218","photograph_type":"D","photographer_name":"John Vachon","caption":"San Augustine, Texas. Sheriff Halberd cleaning his gun in his office","year":"1943","month":"4","vanderbilt_level1":"Organized Society","vanderbilt_level2":"Government","vanderbilt_level3":"Law","lot_number":"688","city":"San Augustine","county":"San Augustine County","state":"Texas","country":"United States","longitude":"-94.1060282","latitude":"31.5299029","fips_code":"48015","img_large_path":"fsa/8d17000/8d17600/8d17691v.jpg","img_medium_path":"fsa/8d17000/8d17600/8d17691r.jpg","img_thumb_img":"fsa/8d17000/8d17600/8d17691_150px.jpg"},{"loc_item_link":"owi2001026352/PP","call_number":"LC-USW3-025219","photograph_type":"D","photographer_name":"John Vachon","caption":"San Augustine, Texas. The waiting room in the railroad station","year":"1943","month":"4","vanderbilt_level1":"Transportation","vanderbilt_level2":"Railroads","vanderbilt_level3":"Railroad Stations","lot_number":"688","city":"San Augustine","county":"San Augustine County","state":"Texas","country":"United States","longitude":"-94.1060282","latitude":"31.5299029","fips_code":"48015","img_large_path":"fsa/8d17000/8d17600/8d17692v.jpg","img_medium_path":"fsa/8d17000/8d17600/8d17692r.jpg","img_thumb_img":"fsa/8d17000/8d17600/8d17692_150px.jpg"},{"loc_item_link":"owi2001026353/PP","call_number":"LC-USW3-025220","photograph_type":"D","photographer_name":"John Vachon","caption":"San Augustine, Texas. The waiting room in the railroad station","year":"1943","month":"4","vanderbilt_level1":"Transportation","vanderbilt_level2":"Railroads","vanderbilt_level3":"Railroad Stations","lot_number":"688","city":"San Augustine","county":"San Augustine County","state":"Texas","country":"United States","longitude":"-94.1060282","latitude":"31.5299029","fips_code":"48015","img_large_path":"fsa/8d17000/8d17600/8d17693v.jpg","img_medium_path":"fsa/8d17000/8d17600/8d17693r.jpg","img_thumb_img":"fsa/8d17000/8d17600/8d17693_150px.jpg"},{"loc_item_link":"owi2001026355/PP","call_number":"LC-USW3-025222","photograph_type":"D","photographer_name":"John Vachon","caption":"San Augustine, Texas. People on the main street on Saturday afternoon","year":"1943","month":"4","vanderbilt_level1":"People As Such","vanderbilt_level2":"Groups and Individuals","vanderbilt_level3":"In the Streets","lot_number":"688","city":"San Augustine","county":"San Augustine County","state":"Texas","country":"United States","longitude":"-94.1060282","latitude":"31.5299029","fips_code":"48015","img_large_path":"fsa/8d17000/8d17600/8d17695v.jpg","img_medium_path":"fsa/8d17000/8d17600/8d17695r.jpg","img_thumb_img":"fsa/8d17000/8d17600/8d17695_150px.jpg"},{"loc_item_link":"owi2001026357/PP","call_number":"LC-USW3-025224","photograph_type":"D","photographer_name":"John Vachon","caption":"San Augustine, Texas. The courthouse square on Saturday afternoon","year":"1943","month":"4","vanderbilt_level1":"Cities and Towns","vanderbilt_level2":"Towns and Small Cities","vanderbilt_level3":"Signs and Historical Markers","lot_number":"688","city":"San Augustine","county":"San Augustine County","state":"Texas","country":"United States","longitude":"-94.1060282","latitude":"31.5299029","fips_code":"48015","img_large_path":"fsa/8d17000/8d17600/8d17697v.jpg","img_medium_path":"fsa/8d17000/8d17600/8d17697r.jpg","img_thumb_img":"fsa/8d17000/8d17600/8d17697_150px.jpg"},{"loc_item_link":"owi2001026358/PP","call_number":"LC-USW3-025225","photograph_type":"D","photographer_name":"John Vachon","caption":"San Augustine, Texas. The courthouse square on Saturday afternoon","year":"1943","month":"4","vanderbilt_level1":"Cities and Towns","vanderbilt_level2":"Towns and Small Cities","vanderbilt_level3":"Signs and Historical Markers","lot_number":"688","city":"San Augustine","county":"San Augustine County","state":"Texas","country":"United States","longitude":"-94.1060282","latitude":"31.5299029","fips_code":"48015","img_large_path":"fsa/8d17000/8d17600/8d17698v.jpg","img_medium_path":"fsa/8d17000/8d17600/8d17698r.jpg","img_thumb_img":"fsa/8d17000/8d17600/8d17698_150px.jpg"},{"loc_item_link":"owi2001026360/PP","call_number":"LC-USW3-025227","photograph_type":"D","photographer_name":"John Vachon","caption":"San Augustine, Texas. The register of deeds","year":"1943","month":"4","vanderbilt_level1":"Organized Society","vanderbilt_level2":"Government","vanderbilt_level3":"Government","lot_number":"688","city":"San Augustine","county":"San Augustine County","state":"Texas","country":"United States","longitude":"-94.1060282","latitude":"31.5299029","fips_code":"48015","img_large_path":"fsa/8d17000/8d17700/8d17701v.jpg","img_medium_path":"fsa/8d17000/8d17700/8d17701r.jpg","img_thumb_img":"fsa/8d17000/8d17700/8d17701_150px.jpg"},{"loc_item_link":"owi2001026361/PP","call_number":"LC-USW3-025228","photograph_type":"D","photographer_name":"John Vachon","caption":"San Augustine, Texas. The county clerk&#39;s office","year":"1943","month":"4","vanderbilt_level1":"Organized Society","vanderbilt_level2":"Government","vanderbilt_level3":"Government","lot_number":"688","city":"San Augustine","county":"San Augustine County","state":"Texas","country":"United States","longitude":"-94.1060282","latitude":"31.5299029","fips_code":"48015","img_large_path":"fsa/8d17000/8d17700/8d17702v.jpg","img_medium_path":"fsa/8d17000/8d17700/8d17702r.jpg","img_thumb_img":"fsa/8d17000/8d17700/8d17702_150px.jpg"},{"loc_item_link":"owi2001026363/PP","call_number":"LC-USW3-025230","photograph_type":"D","photographer_name":"John Vachon","caption":"San Augustine, Texas. The edge of town","year":"1943","month":"4","vanderbilt_level1":"Cities and Towns","vanderbilt_level2":"Towns and Small Cities","vanderbilt_level3":"Towns","lot_number":"688","city":"San Augustine","county":"San Augustine County","state":"Texas","country":"United States","longitude":"-94.1060282","latitude":"31.5299029","fips_code":"48015","img_large_path":"fsa/8d17000/8d17700/8d17704v.jpg","img_medium_path":"fsa/8d17000/8d17700/8d17704r.jpg","img_thumb_img":"fsa/8d17000/8d17700/8d17704_150px.jpg"},{"loc_item_link":"owi2001026364/PP","call_number":"LC-USW3-025231","photograph_type":"D","photographer_name":"John Vachon","caption":"San Augustine, Texas. Watching livestock being unloaded into pens for the Monday auction","year":"1943","month":"4","vanderbilt_level1":"Work","vanderbilt_level2":"Selling and Distribution","vanderbilt_level3":"Auctions","lot_number":"688","city":"San Augustine","county":"San Augustine County","state":"Texas","country":"United States","longitude":"-94.1060282","latitude":"31.5299029","fips_code":"48015","img_large_path":"fsa/8d17000/8d17700/8d17705v.jpg","img_medium_path":"fsa/8d17000/8d17700/8d17705r.jpg","img_thumb_img":"fsa/8d17000/8d17700/8d17705_150px.jpg"},{"loc_item_link":"owi2001026365/PP","call_number":"LC-USW3-025232","photograph_type":"D","photographer_name":"John Vachon","caption":"San Augustine, Texas. Livestock being unloaded into pens for the Monday auction","year":"1943","month":"4","vanderbilt_level1":"Work","vanderbilt_level2":"Selling and Distribution","vanderbilt_level3":"Auctions","lot_number":"688","city":"San Augustine","county":"San Augustine County","state":"Texas","country":"United States","longitude":"-94.1060282","latitude":"31.5299029","fips_code":"48015","img_large_path":"fsa/8d17000/8d17700/8d17706v.jpg","img_medium_path":"fsa/8d17000/8d17700/8d17706r.jpg","img_thumb_img":"fsa/8d17000/8d17700/8d17706_150px.jpg"},{"loc_item_link":"owi2001026366/PP","call_number":"LC-USW3-025233","photograph_type":"D","photographer_name":"John Vachon","caption":"San Augustine, Texas. Men talking on a street corner","year":"1943","month":"4","vanderbilt_level1":"People As Such","vanderbilt_level2":"Groups and Individuals","vanderbilt_level3":"In the Streets","lot_number":"688","city":"San Augustine","county":"San Augustine County","state":"Texas","country":"United States","longitude":"-94.1060282","latitude":"31.5299029","fips_code":"48015","img_large_path":"fsa/8d17000/8d17700/8d17707v.jpg","img_medium_path":"fsa/8d17000/8d17700/8d17707r.jpg","img_thumb_img":"fsa/8d17000/8d17700/8d17707_150px.jpg"},{"loc_item_link":"owi2001026367/PP","call_number":"LC-USW3-025234","photograph_type":"D","photographer_name":"John Vachon","caption":"San Augustine, Texas. A building on the main street which was demolished by the March tornado","year":"1943","month":"4","vanderbilt_level1":"The Land","vanderbilt_level2":"Weather, Floods, Waterways","vanderbilt_level3":"Hurricanes","lot_number":"688","city":"San Augustine","county":"San Augustine County","state":"Texas","country":"United States","longitude":"-94.1060282","latitude":"31.5299029","fips_code":"48015","img_large_path":"fsa/8d17000/8d17700/8d17708v.jpg","img_medium_path":"fsa/8d17000/8d17700/8d17708r.jpg","img_thumb_img":"fsa/8d17000/8d17700/8d17708_150px.jpg"},{"loc_item_link":"owi2001026368/PP","call_number":"LC-USW3-025235","photograph_type":"D","photographer_name":"John Vachon","caption":"San Augustine, Texas. Dr. Rulfs in his office","year":"1943","month":"4","vanderbilt_level1":"Medicine and Health","vanderbilt_level2":"General","vanderbilt_level3":"Physicians","lot_number":"688","city":"San Augustine","county":"San Augustine County","state":"Texas","country":"United States","longitude":"-94.1060282","latitude":"31.5299029","fips_code":"48015","img_large_path":"fsa/8d17000/8d17700/8d17709v.jpg","img_medium_path":"fsa/8d17000/8d17700/8d17709r.jpg","img_thumb_img":"fsa/8d17000/8d17700/8d17709_150px.jpg"},{"loc_item_link":"owi2001026370/PP","call_number":"LC-USW3-025237","photograph_type":"D","photographer_name":"John Vachon","caption":"San Augustine, Texas. The town from the cemetery","year":"1943","month":"4","vanderbilt_level1":"Cities and Towns","vanderbilt_level2":"Towns and Small Cities","vanderbilt_level3":"Cemeteries","lot_number":"688","city":"San Augustine","county":"San Augustine County","state":"Texas","country":"United States","longitude":"-94.1060282","latitude":"31.5299029","fips_code":"48015","img_large_path":"fsa/8d17000/8d17700/8d17711v.jpg","img_medium_path":"fsa/8d17000/8d17700/8d17711r.jpg","img_thumb_img":"fsa/8d17000/8d17700/8d17711_150px.jpg"}]