[{"loc_item_link":"fsa2000055223/PP","call_number":"LC-USF34-084177","photograph_type":"C","photographer_name":"John Collier","caption":"Batavia, New York. Elba FSA (Farm Security Administration) farm labor camp. Tent being put up to house the migrants","year":"1942","month":"9","vanderbilt_level1":"Homes and Living Conditions","vanderbilt_level2":"Temporary Abodes","vanderbilt_level3":"Tents, Shacks","lot_number":"63","city":"Batavia","county":"Genesee County","state":"New York","country":"United States","longitude":"-78.1875167","latitude":"42.9981156","fips_code":"36037","img_large_path":"fsa/8c28000/8c28000/8c28062v.jpg","img_medium_path":"fsa/8c28000/8c28000/8c28062r.jpg","img_thumb_img":"fsa/8c28000/8c28000/8c28062_150px.jpg"},{"loc_item_link":"fsa2000055228/PP","call_number":"LC-USF34-084182","photograph_type":"E","photographer_name":"John Collier","caption":"Special train carrying agricultural workers to upper New York state to work in the harvest","year":"1942","month":"9","vanderbilt_level1":"Transportation","vanderbilt_level2":"Railroads","vanderbilt_level3":"Passengers","lot_number":"62","city":"","county":"","state":"","country":"","longitude":"NA","latitude":"NA","fips_code":"NA","img_large_path":"fsa/8c34000/8c34200/8c34236v.jpg","img_medium_path":"fsa/8c34000/8c34200/8c34236r.jpg","img_thumb_img":"fsa/8c34000/8c34200/8c34236_150px.jpg"},{"loc_item_link":"fsa2000055229/PP","call_number":"LC-USF34-084183","photograph_type":"E","photographer_name":"John Collier","caption":"Picking up the Clay section of the special train carrying agricultural workers to upper New York state","year":"1942","month":"9","vanderbilt_level1":"","vanderbilt_level2":"","vanderbilt_level3":"","lot_number":"62","city":"","county":"","state":"","country":"","longitude":"NA","latitude":"NA","fips_code":"NA","img_large_path":"fsa/8c34000/8c34200/8c34237v.jpg","img_medium_path":"fsa/8c34000/8c34200/8c34237r.jpg","img_thumb_img":"fsa/8c34000/8c34200/8c34237_150px.jpg"},{"loc_item_link":"fsa2000055230/PP","call_number":"LC-USF34-084184","photograph_type":"E","photographer_name":"John Collier","caption":"Picking up the Clay section of the special train carrying agricultural workers to upper New York state","year":"1942","month":"9","vanderbilt_level1":"Transportation","vanderbilt_level2":"Railroads","vanderbilt_level3":"Passengers","lot_number":"62","city":"","county":"","state":"","country":"","longitude":"NA","latitude":"NA","fips_code":"NA","img_large_path":"fsa/8c34000/8c34200/8c34238v.jpg","img_medium_path":"fsa/8c34000/8c34200/8c34238r.jpg","img_thumb_img":"fsa/8c34000/8c34200/8c34238_150px.jpg"},{"loc_item_link":"fsa2000055231/PP","call_number":"LC-USF34-084185","photograph_type":"E","photographer_name":"John Collier","caption":"Picking up the Clay section of the special train carrying agricultural workers to upper New York state","year":"1942","month":"9","vanderbilt_level1":"","vanderbilt_level2":"","vanderbilt_level3":"","lot_number":"62","city":"","county":"","state":"","country":"","longitude":"NA","latitude":"NA","fips_code":"NA","img_large_path":"fsa/8c34000/8c34200/8c34239v.jpg","img_medium_path":"fsa/8c34000/8c34200/8c34239r.jpg","img_thumb_img":"fsa/8c34000/8c34200/8c34239_150px.jpg"},{"loc_item_link":"fsa2000055232/PP","call_number":"LC-USF34-084186","photograph_type":"E","photographer_name":"John Collier","caption":"Picking up the Clay section of the special train carrying agricultural workers to upper New York state","year":"1942","month":"9","vanderbilt_level1":"Transportation","vanderbilt_level2":"Railroads","vanderbilt_level3":"Passengers","lot_number":"62","city":"","county":"","state":"","country":"","longitude":"NA","latitude":"NA","fips_code":"NA","img_large_path":"fsa/8c34000/8c34200/8c34240v.jpg","img_medium_path":"fsa/8c34000/8c34200/8c34240r.jpg","img_thumb_img":"fsa/8c34000/8c34200/8c34240_150px.jpg"},{"loc_item_link":"fsa2000055233/PP","call_number":"LC-USF34-084187","photograph_type":"E","photographer_name":"John Collier","caption":"Picking up the Clay section of the special train carrying agricultural workers to upper New York state","year":"1942","month":"9","vanderbilt_level1":"Transportation","vanderbilt_level2":"Railroads","vanderbilt_level3":"Passengers","lot_number":"62","city":"","county":"","state":"","country":"","longitude":"NA","latitude":"NA","fips_code":"NA","img_large_path":"fsa/8c34000/8c34200/8c34241v.jpg","img_medium_path":"fsa/8c34000/8c34200/8c34241r.jpg","img_thumb_img":"fsa/8c34000/8c34200/8c34241_150px.jpg"},{"loc_item_link":"fsa2000055234/PP","call_number":"LC-USF34-084188","photograph_type":"E","photographer_name":"John Collier","caption":"Richwood, West Virginia. These boys stayed at home when the special train left Richwood carrying agricultural workers to upper New York state to help in the harvest","year":"1942","month":"9","vanderbilt_level1":"People As Such","vanderbilt_level2":"Children","vanderbilt_level3":"Groups of Children","lot_number":"62","city":"Richwood","county":"Nicholas County","state":"West Virginia","country":"United States","longitude":"-80.5331411","latitude":"38.2248367","fips_code":"54067","img_large_path":"fsa/8c34000/8c34200/8c34242v.jpg","img_medium_path":"fsa/8c34000/8c34200/8c34242r.jpg","img_thumb_img":"fsa/8c34000/8c34200/8c34242_150px.jpg"},{"loc_item_link":"fsa2000055236/PP","call_number":"LC-USF34-084190","photograph_type":"E","photographer_name":"John Collier","caption":"Batavia, New York. Elba FSA (Farm Security Administration) farm labor camp. Man on the left is a former relief client who was transported from New York City to work in the crops. Man to right is from West Virginia","year":"1942","month":"9","vanderbilt_level1":"Organized Society","vanderbilt_level2":"Government and Other Organized Aid","vanderbilt_level3":"Farm Security Administration Camps","lot_number":"63","city":"Batavia","county":"Genesee County","state":"New York","country":"United States","longitude":"-78.1875167","latitude":"42.9981156","fips_code":"36037","img_large_path":"fsa/8c34000/8c34200/8c34244v.jpg","img_medium_path":"fsa/8c34000/8c34200/8c34244r.jpg","img_thumb_img":"fsa/8c34000/8c34200/8c34244_150px.jpg"},{"loc_item_link":"fsa2000055237/PP","call_number":"LC-USF34-084191","photograph_type":"E","photographer_name":"John Collier","caption":"Richwood, West Virginia. Saying goodbye, Richwood station","year":"1942","month":"9","vanderbilt_level1":"Transportation","vanderbilt_level2":"Railroads","vanderbilt_level3":"People on Platforms","lot_number":"62","city":"Richwood","county":"Nicholas County","state":"West Virginia","country":"United States","longitude":"-80.5331411","latitude":"38.2248367","fips_code":"54067","img_large_path":"fsa/8c34000/8c34200/8c34245v.jpg","img_medium_path":"fsa/8c34000/8c34200/8c34245r.jpg","img_thumb_img":"fsa/8c34000/8c34200/8c34245_150px.jpg"},{"loc_item_link":"fsa2000055238/PP","call_number":"LC-USF34-084192","photograph_type":"E","photographer_name":"John Collier","caption":"Richwood, West Virginia. Saying goodbye, Richwood station","year":"1942","month":"9","vanderbilt_level1":"Transportation","vanderbilt_level2":"Railroads","vanderbilt_level3":"Passengers","lot_number":"62","city":"Richwood","county":"Nicholas County","state":"West Virginia","country":"United States","longitude":"-80.5331411","latitude":"38.2248367","fips_code":"54067","img_large_path":"fsa/8c34000/8c34200/8c34246v.jpg","img_medium_path":"fsa/8c34000/8c34200/8c34246r.jpg","img_thumb_img":"fsa/8c34000/8c34200/8c34246_150px.jpg"},{"loc_item_link":"fsa2000055239/PP","call_number":"LC-USF34-084193","photograph_type":"E","photographer_name":"John Collier","caption":"Richwood, West Virginia. Saying goodbye, Richwood station","year":"1942","month":"9","vanderbilt_level1":"Transportation","vanderbilt_level2":"Railroads","vanderbilt_level3":"Passengers","lot_number":"62","city":"Richwood","county":"Nicholas County","state":"West Virginia","country":"United States","longitude":"-80.5331411","latitude":"38.2248367","fips_code":"54067","img_large_path":"fsa/8c34000/8c34200/8c34247v.jpg","img_medium_path":"fsa/8c34000/8c34200/8c34247r.jpg","img_thumb_img":"fsa/8c34000/8c34200/8c34247_150px.jpg"},{"loc_item_link":"fsa2000055240/PP","call_number":"LC-USF34-084194","photograph_type":"E","photographer_name":"John Collier","caption":"Batavia, New York. Elba FSA (Farm Security Administration) farm labor camp. Girls from Richwood, West Virginia.","year":"1942","month":"9","vanderbilt_level1":"Organized Society","vanderbilt_level2":"Government and Other Organized Aid","vanderbilt_level3":"Farm Security Administration Camps","lot_number":"63","city":"Batavia","county":"Genesee County","state":"New York","country":"United States","longitude":"-78.1875167","latitude":"42.9981156","fips_code":"36037","img_large_path":"fsa/8c34000/8c34200/8c34248v.jpg","img_medium_path":"fsa/8c34000/8c34200/8c34248r.jpg","img_thumb_img":"fsa/8c34000/8c34200/8c34248_150px.jpg"},{"loc_item_link":"fsa2000055242/PP","call_number":"LC-USF34-084196","photograph_type":"E","photographer_name":"John Collier","caption":"Albion, New York (vicinity). Harvesting tomatoes on Nesbitt&#39;s farm","year":"1942","month":"9","vanderbilt_level1":"","vanderbilt_level2":"","vanderbilt_level3":"","lot_number":"63","city":"Albion","county":"Orleans County","state":"New York","country":"United States","longitude":"-78.8894804","latitude":"42.2895063","fips_code":"36073","img_large_path":"fsa/8c34000/8c34200/8c34250v.jpg","img_medium_path":"fsa/8c34000/8c34200/8c34250r.jpg","img_thumb_img":"fsa/8c34000/8c34200/8c34250_150px.jpg"},{"loc_item_link":"fsa2000055243/PP","call_number":"LC-USF34-084197","photograph_type":"E","photographer_name":"John Collier","caption":"Batavia, New York (vicinity). West Virginia crew of pickers en route to the muck fields","year":"1942","month":"9","vanderbilt_level1":"Transportation","vanderbilt_level2":"Road Transport","vanderbilt_level3":"Trucks Transporting People","lot_number":"63","city":"Batavia","county":"Genesee County","state":"New York","country":"United States","longitude":"-78.1875167","latitude":"42.9981156","fips_code":"36037","img_large_path":"fsa/8c34000/8c34200/8c34251v.jpg","img_medium_path":"fsa/8c34000/8c34200/8c34251r.jpg","img_thumb_img":"fsa/8c34000/8c34200/8c34251_150px.jpg"},{"loc_item_link":"fsa2000055244/PP","call_number":"LC-USF34-084198","photograph_type":"E","photographer_name":"John Collier","caption":"Albion, New York (vicinity). Charles R. Nesbitt who hired the Friend family to work on his farm at forty cents an hour, with a five cents an hour bonus if they stay thirty days","year":"1942","month":"9","vanderbilt_level1":"People As Such","vanderbilt_level2":"Groups and Individuals","vanderbilt_level3":"Farmers and Farmers' Heads","lot_number":"63","city":"Albion","county":"Orleans County","state":"New York","country":"United States","longitude":"-78.8894804","latitude":"42.2895063","fips_code":"36073","img_large_path":"fsa/8c34000/8c34200/8c34252v.jpg","img_medium_path":"fsa/8c34000/8c34200/8c34252r.jpg","img_thumb_img":"fsa/8c34000/8c34200/8c34252_150px.jpg"},{"loc_item_link":"fsa2000055247/PP","call_number":"LC-USF34-084201","photograph_type":"E","photographer_name":"John Collier","caption":"Albion, New York (vicinity). Harvesting tomatoes on Nesbitt&#39;s farm","year":"1942","month":"9","vanderbilt_level1":"","vanderbilt_level2":"","vanderbilt_level3":"","lot_number":"63","city":"Albion","county":"Orleans County","state":"New York","country":"United States","longitude":"-78.8894804","latitude":"42.2895063","fips_code":"36073","img_large_path":"fsa/8c34000/8c34200/8c34255v.jpg","img_medium_path":"fsa/8c34000/8c34200/8c34255r.jpg","img_thumb_img":"fsa/8c34000/8c34200/8c34255_150px.jpg"},{"loc_item_link":"fsa2000055250/PP","call_number":"LC-USF34-084204","photograph_type":"E","photographer_name":"John Collier","caption":"Batavia, New York. Elba FSA (Farm Security Administration) farm labor camp. Migrant waiting for work in front of the United States employment service office","year":"1942","month":"9","vanderbilt_level1":"Organized Society","vanderbilt_level2":"Government and Other Organized Aid","vanderbilt_level3":"Migratory Workers, Farm Labor Camps","lot_number":"63","city":"Batavia","county":"Genesee County","state":"New York","country":"United States","longitude":"-78.1875167","latitude":"42.9981156","fips_code":"36037","img_large_path":"fsa/8c34000/8c34200/8c34258v.jpg","img_medium_path":"fsa/8c34000/8c34200/8c34258r.jpg","img_thumb_img":"fsa/8c34000/8c34200/8c34258_150px.jpg"},{"loc_item_link":"fsa2000055252/PP","call_number":"LC-USF34-084206","photograph_type":"E","photographer_name":"John Collier","caption":"Batavia, New York. Elba FSA (Farm Security Administration) farm labor camp. Ray Mork, FSA official, addressing West Virginia migrants on the night of their arrival","year":"1942","month":"9","vanderbilt_level1":"Organized Society","vanderbilt_level2":"Government and Other Organized Aid","vanderbilt_level3":"Migratory Workers, Farm Labor Camps","lot_number":"63","city":"Batavia","county":"Genesee County","state":"New York","country":"United States","longitude":"-78.1875167","latitude":"42.9981156","fips_code":"36037","img_large_path":"fsa/8c34000/8c34200/8c34260v.jpg","img_medium_path":"fsa/8c34000/8c34200/8c34260r.jpg","img_thumb_img":"fsa/8c34000/8c34200/8c34260_150px.jpg"},{"loc_item_link":"fsa2000055578/PP","call_number":"LC-USF34-090320","photograph_type":"D","photographer_name":"John Collier","caption":"Washington, D.C. Preparing the defense bond sales photomural to be installed in the Grand Central terminal, New York, in the photographic laboratory of the FSA (Farm Security Administration). Copying the exact scale paste-up to produce the negative for the final enlargements; this work was done in the laboratory of the United States Coast and Geodetic Society","year":"1941","month":"NA","vanderbilt_level1":"Work","vanderbilt_level2":"Processing and Manufacturing","vanderbilt_level3":"Photo Murals","lot_number":"263","city":"Washington (DC)","county":"US.DC.001","state":"District of Columbia","country":"United States","longitude":"-77.0002539","latitude":"38.9170559","fips_code":"11001","img_large_path":"fsa/8c28000/8c28200/8c28279v.jpg","img_medium_path":"fsa/8c28000/8c28200/8c28279r.jpg","img_thumb_img":"fsa/8c28000/8c28200/8c28279_150px.jpg"},{"loc_item_link":"owi2001002635/PP","call_number":"LC-USW3-000346","photograph_type":"C","photographer_name":"John Collier","caption":"Washington, D.C. Campus of Howard University","year":"1942","month":"NA","vanderbilt_level1":"Itellectual and Creative Activity","vanderbilt_level2":"General","vanderbilt_level3":"University, College Buildings","lot_number":"166","city":"Washington (DC)","county":"US.DC.001","state":"District of Columbia","country":"United States","longitude":"-77.0002539","latitude":"38.9170559","fips_code":"11001","img_large_path":"fsa/8d44000/8d44800/8d44880v.jpg","img_medium_path":"fsa/8d44000/8d44800/8d44880r.jpg","img_thumb_img":"fsa/8d44000/8d44800/8d44880_150px.jpg"},{"loc_item_link":"owi2001002639/PP","call_number":"LC-USW3-000350","photograph_type":"C","photographer_name":"John Collier","caption":"Washington, D.C. Campus of Howard University","year":"1942","month":"NA","vanderbilt_level1":"Itellectual and Creative Activity","vanderbilt_level2":"General","vanderbilt_level3":"University, College Buildings","lot_number":"166","city":"Washington (DC)","county":"US.DC.001","state":"District of Columbia","country":"United States","longitude":"-77.0002539","latitude":"38.9170559","fips_code":"11001","img_large_path":"fsa/8d44000/8d44800/8d44884v.jpg","img_medium_path":"fsa/8d44000/8d44800/8d44884r.jpg","img_thumb_img":"fsa/8d44000/8d44800/8d44884_150px.jpg"},{"loc_item_link":"owi2001002641/PP","call_number":"LC-USW3-000352","photograph_type":"C","photographer_name":"John Collier","caption":"Washington, D.C. Howard University students","year":"1942","month":"NA","vanderbilt_level1":"","vanderbilt_level2":"","vanderbilt_level3":"","lot_number":"166","city":"Washington (DC)","county":"US.DC.001","state":"District of Columbia","country":"United States","longitude":"-77.0002539","latitude":"38.9170559","fips_code":"11001","img_large_path":"fsa/8d44000/8d44800/8d44886v.jpg","img_medium_path":"fsa/8d44000/8d44800/8d44886r.jpg","img_thumb_img":"fsa/8d44000/8d44800/8d44886_150px.jpg"},{"loc_item_link":"owi2001002642/PP","call_number":"LC-USW3-000353","photograph_type":"C","photographer_name":"John Collier","caption":"Washington, D.C. Howard University students","year":"1942","month":"NA","vanderbilt_level1":"","vanderbilt_level2":"","vanderbilt_level3":"","lot_number":"166","city":"Washington (DC)","county":"US.DC.001","state":"District of Columbia","country":"United States","longitude":"-77.0002539","latitude":"38.9170559","fips_code":"11001","img_large_path":"fsa/8d02000/8d02800/8d02832v.jpg","img_medium_path":"fsa/8d02000/8d02800/8d02832r.jpg","img_thumb_img":"fsa/8d02000/8d02800/8d02832_150px.jpg"},{"loc_item_link":"owi2001002645/PP","call_number":"LC-USW3-000356","photograph_type":"C","photographer_name":"John Collier","caption":"Washington, D.C. Howard University students","year":"1942","month":"NA","vanderbilt_level1":"Itellectual and Creative Activity","vanderbilt_level2":"General","vanderbilt_level3":"University, College Buildings","lot_number":"166","city":"Washington (DC)","county":"US.DC.001","state":"District of Columbia","country":"United States","longitude":"-77.0002539","latitude":"38.9170559","fips_code":"11001","img_large_path":"fsa/8d02000/8d02800/8d02835v.jpg","img_medium_path":"fsa/8d02000/8d02800/8d02835r.jpg","img_thumb_img":"fsa/8d02000/8d02800/8d02835_150px.jpg"},{"loc_item_link":"owi2001002647/PP","call_number":"LC-USW3-000358","photograph_type":"C","photographer_name":"John Collier","caption":"Washington, D.C. Campus of Howard University","year":"1942","month":"NA","vanderbilt_level1":"Itellectual and Creative Activity","vanderbilt_level2":"General","vanderbilt_level3":"University, College Buildings","lot_number":"166","city":"Washington (DC)","county":"US.DC.001","state":"District of Columbia","country":"United States","longitude":"-77.0002539","latitude":"38.9170559","fips_code":"11001","img_large_path":"fsa/8d02000/8d02800/8d02837v.jpg","img_medium_path":"fsa/8d02000/8d02800/8d02837r.jpg","img_thumb_img":"fsa/8d02000/8d02800/8d02837_150px.jpg"},{"loc_item_link":"owi2001002651/PP","call_number":"LC-USW3-000362","photograph_type":"C","photographer_name":"John Collier","caption":"Washington, D.C. Howard University students on the class steps","year":"1942","month":"NA","vanderbilt_level1":"Itellectual and Creative Activity","vanderbilt_level2":"General","vanderbilt_level3":"University, College Buildings","lot_number":"166","city":"Washington (DC)","county":"US.DC.001","state":"District of Columbia","country":"United States","longitude":"-77.0002539","latitude":"38.9170559","fips_code":"11001","img_large_path":"fsa/8d02000/8d02800/8d02841v.jpg","img_medium_path":"fsa/8d02000/8d02800/8d02841r.jpg","img_thumb_img":"fsa/8d02000/8d02800/8d02841_150px.jpg"},{"loc_item_link":"owi2001002654/PP","call_number":"LC-USW3-000365","photograph_type":"C","photographer_name":"John Collier","caption":"Washington, D.C. Howard University students on the classroom steps","year":"1942","month":"NA","vanderbilt_level1":"Itellectual and Creative Activity","vanderbilt_level2":"General","vanderbilt_level3":"University, College Buildings","lot_number":"166","city":"Washington (DC)","county":"US.DC.001","state":"District of Columbia","country":"United States","longitude":"-77.0002539","latitude":"38.9170559","fips_code":"11001","img_large_path":"fsa/8d02000/8d02800/8d02844v.jpg","img_medium_path":"fsa/8d02000/8d02800/8d02844r.jpg","img_thumb_img":"fsa/8d02000/8d02800/8d02844_150px.jpg"},{"loc_item_link":"owi2001002655/PP","call_number":"LC-USW3-000366","photograph_type":"C","photographer_name":"John Collier","caption":"Washington, D.C. Campus of Howard University","year":"1942","month":"NA","vanderbilt_level1":"","vanderbilt_level2":"","vanderbilt_level3":"","lot_number":"166","city":"Washington (DC)","county":"US.DC.001","state":"District of Columbia","country":"United States","longitude":"-77.0002539","latitude":"38.9170559","fips_code":"11001","img_large_path":"fsa/8d02000/8d02800/8d02845v.jpg","img_medium_path":"fsa/8d02000/8d02800/8d02845r.jpg","img_thumb_img":"fsa/8d02000/8d02800/8d02845_150px.jpg"},{"loc_item_link":"owi2001002657/PP","call_number":"LC-USW3-000368","photograph_type":"C","photographer_name":"John Collier","caption":"Washington, D.C. Jewal Mazique [i.e. Jewel] working in the stacks of the Library of Congress","year":"1942","month":"NA","vanderbilt_level1":"Itellectual and Creative Activity","vanderbilt_level2":"General","vanderbilt_level3":"Libraries","lot_number":"296","city":"Washington (DC)","county":"US.DC.001","state":"District of Columbia","country":"United States","longitude":"-77.0002539","latitude":"38.9170559","fips_code":"11001","img_large_path":"fsa/8d02000/8d02800/8d02847v.jpg","img_medium_path":"fsa/8d02000/8d02800/8d02847r.jpg","img_thumb_img":"fsa/8d02000/8d02800/8d02847_150px.jpg"}]