[{"loc_item_link":"owi2001010824/PP","call_number":"LC-USW3-008241","photograph_type":"D","photographer_name":"Russell Lee","caption":"Butte, Montana. Anaconda Copper Mining Company. Large refrigerating and ventilating units are required to lower the mine temperatures","year":"1942","month":"9","vanderbilt_level1":"Work","vanderbilt_level2":"Mining, Oil Wells, Quarrying","vanderbilt_level3":"Copper","lot_number":"NA","city":"Butte","county":"Silver Bow County","state":"Montana","country":"United States","longitude":"-112.5347447","latitude":"46.0038153","fips_code":"30093","img_large_path":"fsa/8d08000/8d08300/8d08382v.jpg","img_medium_path":"fsa/8d08000/8d08300/8d08382r.jpg","img_thumb_img":"fsa/8d08000/8d08300/8d08382_150px.jpg"},{"loc_item_link":"owi2001010825/PP","call_number":"LC-USW3-008242","photograph_type":"D","photographer_name":"Russell Lee","caption":"Gravelly Range, Madison County, Montana. Sheep grazing","year":"1942","month":"9","vanderbilt_level1":"Work","vanderbilt_level2":"Agriculture: Crops, Livestock, Ranches","vanderbilt_level3":"Sheep","lot_number":"27","city":"Gravelly Range","county":"Madison County","state":"Montana","country":"United States","longitude":"-112.3702981","latitude":"46.8307722","fips_code":"30057","img_large_path":"fsa/8d08000/8d08300/8d08383v.jpg","img_medium_path":"fsa/8d08000/8d08300/8d08383r.jpg","img_thumb_img":"fsa/8d08000/8d08300/8d08383_150px.jpg"},{"loc_item_link":"owi2001010826/PP","call_number":"LC-USW3-008243","photograph_type":"D","photographer_name":"Russell Lee","caption":"Gravelly Range, Madison County, Montana. Sheep grazing","year":"1942","month":"9","vanderbilt_level1":"Work","vanderbilt_level2":"Agriculture: Crops, Livestock, Ranches","vanderbilt_level3":"Sheep","lot_number":"27","city":"Gravelly Range","county":"Madison County","state":"Montana","country":"United States","longitude":"-112.3702981","latitude":"46.8307722","fips_code":"30057","img_large_path":"fsa/8d08000/8d08300/8d08384v.jpg","img_medium_path":"fsa/8d08000/8d08300/8d08384r.jpg","img_thumb_img":"fsa/8d08000/8d08300/8d08384_150px.jpg"},{"loc_item_link":"owi2001010827/PP","call_number":"LC-USW3-008244","photograph_type":"D","photographer_name":"Russell Lee","caption":"Gravelly Range, Madison County, Montana. Sheepherder and his horse and dog","year":"1942","month":"9","vanderbilt_level1":"People As Such","vanderbilt_level2":"Groups and Individuals","vanderbilt_level3":"Sheep Ranchers","lot_number":"27","city":"Gravelly Range","county":"Madison County","state":"Montana","country":"United States","longitude":"-112.3702981","latitude":"46.8307722","fips_code":"30057","img_large_path":"fsa/8d08000/8d08300/8d08385v.jpg","img_medium_path":"fsa/8d08000/8d08300/8d08385r.jpg","img_thumb_img":"fsa/8d08000/8d08300/8d08385_150px.jpg"},{"loc_item_link":"owi2001010828/PP","call_number":"LC-USW3-008245","photograph_type":"D","photographer_name":"Russell Lee","caption":"Gravelly Range, Madison County, Montana. Sheep grazing","year":"1942","month":"9","vanderbilt_level1":"Work","vanderbilt_level2":"Agriculture: Crops, Livestock, Ranches","vanderbilt_level3":"Sheep","lot_number":"27","city":"Gravelly Range","county":"Madison County","state":"Montana","country":"United States","longitude":"-112.3702981","latitude":"46.8307722","fips_code":"30057","img_large_path":"fsa/8d08000/8d08300/8d08386v.jpg","img_medium_path":"fsa/8d08000/8d08300/8d08386r.jpg","img_thumb_img":"fsa/8d08000/8d08300/8d08386_150px.jpg"},{"loc_item_link":"owi2001010829/PP","call_number":"LC-USW3-008246","photograph_type":"D","photographer_name":"Russell Lee","caption":"Gravelly Range, Madison County, Montana. Sheep grazing","year":"1942","month":"9","vanderbilt_level1":"Work","vanderbilt_level2":"Agriculture: Crops, Livestock, Ranches","vanderbilt_level3":"Sheep","lot_number":"27","city":"Gravelly Range","county":"Madison County","state":"Montana","country":"United States","longitude":"-112.3702981","latitude":"46.8307722","fips_code":"30057","img_large_path":"fsa/8d08000/8d08300/8d08387v.jpg","img_medium_path":"fsa/8d08000/8d08300/8d08387r.jpg","img_thumb_img":"fsa/8d08000/8d08300/8d08387_150px.jpg"},{"loc_item_link":"owi2001010830/PP","call_number":"LC-USW3-008247","photograph_type":"D","photographer_name":"Russell Lee","caption":"Gravelly Range, Madison County, Montana. Sheep grazing","year":"1942","month":"9","vanderbilt_level1":"Work","vanderbilt_level2":"Agriculture: Crops, Livestock, Ranches","vanderbilt_level3":"Sheep","lot_number":"27","city":"Gravelly Range","county":"Madison County","state":"Montana","country":"United States","longitude":"-112.3702981","latitude":"46.8307722","fips_code":"30057","img_large_path":"fsa/8d08000/8d08300/8d08388v.jpg","img_medium_path":"fsa/8d08000/8d08300/8d08388r.jpg","img_thumb_img":"fsa/8d08000/8d08300/8d08388_150px.jpg"},{"loc_item_link":"owi2001010831/PP","call_number":"LC-USW3-008248","photograph_type":"D","photographer_name":"Russell Lee","caption":"Butte, Montana. Anaconda Copper Mining Company. Copper miners","year":"1942","month":"9","vanderbilt_level1":"People As Such","vanderbilt_level2":"Groups and Individuals","vanderbilt_level3":"Miners","lot_number":"229","city":"Butte","county":"Silver Bow County","state":"Montana","country":"United States","longitude":"-112.5347447","latitude":"46.0038153","fips_code":"30093","img_large_path":"fsa/8d08000/8d08300/8d08389v.jpg","img_medium_path":"fsa/8d08000/8d08300/8d08389r.jpg","img_thumb_img":"fsa/8d08000/8d08300/8d08389_150px.jpg"},{"loc_item_link":"owi2001010832/PP","call_number":"LC-USW3-008249","photograph_type":"D","photographer_name":"Russell Lee","caption":"Butte, Montana","year":"1942","month":"9","vanderbilt_level1":"Cities and Towns","vanderbilt_level2":"Towns and Small Cities","vanderbilt_level3":"Overall Views","lot_number":"229","city":"Butte","county":"Silver Bow County","state":"Montana","country":"United States","longitude":"-112.5347447","latitude":"46.0038153","fips_code":"30093","img_large_path":"fsa/8d08000/8d08300/8d08390v.jpg","img_medium_path":"fsa/8d08000/8d08300/8d08390r.jpg","img_thumb_img":"fsa/8d08000/8d08300/8d08390_150px.jpg"},{"loc_item_link":"owi2001010834/PP","call_number":"LC-USW3-008251","photograph_type":"D","photographer_name":"Russell Lee","caption":"Butte, Montana. The town is dominated by the headframes of copper mines","year":"1942","month":"9","vanderbilt_level1":"Cities and Towns","vanderbilt_level2":"Towns and Small Cities","vanderbilt_level3":"Overall Views","lot_number":"229","city":"Butte","county":"Silver Bow County","state":"Montana","country":"United States","longitude":"-112.5347447","latitude":"46.0038153","fips_code":"30093","img_large_path":"fsa/8d08000/8d08300/8d08392v.jpg","img_medium_path":"fsa/8d08000/8d08300/8d08392r.jpg","img_thumb_img":"fsa/8d08000/8d08300/8d08392_150px.jpg"},{"loc_item_link":"owi2001010835/PP","call_number":"LC-USW3-008252","photograph_type":"D","photographer_name":"Russell Lee","caption":"Butte, Montana. Anaconda Copper Mining Company. Drilling in the ore body of a copper mine","year":"1942","month":"9","vanderbilt_level1":"Work","vanderbilt_level2":"Mining, Oil Wells, Quarrying","vanderbilt_level3":"Drilling, Blasting, Mucking","lot_number":"229","city":"Butte","county":"Silver Bow County","state":"Montana","country":"United States","longitude":"-112.5347447","latitude":"46.0038153","fips_code":"30093","img_large_path":"fsa/8d08000/8d08300/8d08393v.jpg","img_medium_path":"fsa/8d08000/8d08300/8d08393r.jpg","img_thumb_img":"fsa/8d08000/8d08300/8d08393_150px.jpg"},{"loc_item_link":"owi2001010836/PP","call_number":"LC-USW3-008253","photograph_type":"D","photographer_name":"Russell Lee","caption":"Butte, Montana. Anaconda Copper Mining Company. Tamping in the powder and placing wires for blasting in copper mine","year":"1942","month":"9","vanderbilt_level1":"Work","vanderbilt_level2":"Mining, Oil Wells, Quarrying","vanderbilt_level3":"Drilling, Blasting, Mucking","lot_number":"229","city":"Butte","county":"Silver Bow County","state":"Montana","country":"United States","longitude":"-112.5347447","latitude":"46.0038153","fips_code":"30093","img_large_path":"fsa/8d08000/8d08300/8d08394v.jpg","img_medium_path":"fsa/8d08000/8d08300/8d08394r.jpg","img_thumb_img":"fsa/8d08000/8d08300/8d08394_150px.jpg"},{"loc_item_link":"owi2001010837/PP","call_number":"LC-USW3-008254","photograph_type":"D","photographer_name":"Russell Lee","caption":"Butte, Montana","year":"1942","month":"9","vanderbilt_level1":"","vanderbilt_level2":"","vanderbilt_level3":"","lot_number":"229","city":"Butte","county":"Silver Bow County","state":"Montana","country":"United States","longitude":"-112.5347447","latitude":"46.0038153","fips_code":"30093","img_large_path":"fsa/8d08000/8d08300/8d08395v.jpg","img_medium_path":"fsa/8d08000/8d08300/8d08395r.jpg","img_thumb_img":"fsa/8d08000/8d08300/8d08395_150px.jpg"},{"loc_item_link":"owi2001010838/PP","call_number":"LC-USW3-008255","photograph_type":"D","photographer_name":"Russell Lee","caption":"Butte, Montana. Anaconda Copper Mining Company. Drilling in the ore body of a copper mine","year":"1942","month":"9","vanderbilt_level1":"Work","vanderbilt_level2":"Mining, Oil Wells, Quarrying","vanderbilt_level3":"Drilling, Blasting, Mucking","lot_number":"229","city":"Butte","county":"Silver Bow County","state":"Montana","country":"United States","longitude":"-112.5347447","latitude":"46.0038153","fips_code":"30093","img_large_path":"fsa/8d08000/8d08300/8d08396v.jpg","img_medium_path":"fsa/8d08000/8d08300/8d08396r.jpg","img_thumb_img":"fsa/8d08000/8d08300/8d08396_150px.jpg"},{"loc_item_link":"owi2001010840/PP","call_number":"LC-USW3-008257","photograph_type":"D","photographer_name":"Russell Lee","caption":"Butte, Montana. Anaconda Copper Mining Company. Miner using automatic mucking machine to load ore cars in a copper mine","year":"1942","month":"9","vanderbilt_level1":"Work","vanderbilt_level2":"Mining, Oil Wells, Quarrying","vanderbilt_level3":"Drilling, Blasting, Mucking","lot_number":"229","city":"Butte","county":"Silver Bow County","state":"Montana","country":"United States","longitude":"-112.5347447","latitude":"46.0038153","fips_code":"30093","img_large_path":"fsa/8d08000/8d08300/8d08398v.jpg","img_medium_path":"fsa/8d08000/8d08300/8d08398r.jpg","img_thumb_img":"fsa/8d08000/8d08300/8d08398_150px.jpg"},{"loc_item_link":"owi2001010841/PP","call_number":"LC-USW3-008258","photograph_type":"D","photographer_name":"Russell Lee","caption":"Butte, Montana. Anaconda Copper Mining Company. Miner using automatic mucking machine to load ore cars in a copper mine","year":"1942","month":"9","vanderbilt_level1":"Work","vanderbilt_level2":"Mining, Oil Wells, Quarrying","vanderbilt_level3":"Drilling, Blasting, Mucking","lot_number":"229","city":"Butte","county":"Silver Bow County","state":"Montana","country":"United States","longitude":"-112.5347447","latitude":"46.0038153","fips_code":"30093","img_large_path":"fsa/8d08000/8d08300/8d08399v.jpg","img_medium_path":"fsa/8d08000/8d08300/8d08399r.jpg","img_thumb_img":"fsa/8d08000/8d08300/8d08399_150px.jpg"},{"loc_item_link":"owi2001010843/PP","call_number":"LC-USW3-008260","photograph_type":"D","photographer_name":"Russell Lee","caption":"Butte, Montana. Anaconda Copper Mining Company. Miner using automatic mucking machine to load cars in a copper mine","year":"1942","month":"9","vanderbilt_level1":"Work","vanderbilt_level2":"Mining, Oil Wells, Quarrying","vanderbilt_level3":"Drilling, Blasting, Mucking","lot_number":"229","city":"Butte","county":"Silver Bow County","state":"Montana","country":"United States","longitude":"-112.5347447","latitude":"46.0038153","fips_code":"30093","img_large_path":"fsa/8d08000/8d08400/8d08402v.jpg","img_medium_path":"fsa/8d08000/8d08400/8d08402r.jpg","img_thumb_img":"fsa/8d08000/8d08400/8d08402_150px.jpg"},{"loc_item_link":"owi2001010845/PP","call_number":"LC-USW3-008262","photograph_type":"D","photographer_name":"Russell Lee","caption":"Butte, Montana. Anaconda Copper Mining Company. Miner using automatic mucking machine to load ore cars in a copper mine","year":"1942","month":"9","vanderbilt_level1":"Work","vanderbilt_level2":"Mining, Oil Wells, Quarrying","vanderbilt_level3":"Drilling, Blasting, Mucking","lot_number":"229","city":"Butte","county":"Silver Bow County","state":"Montana","country":"United States","longitude":"-112.5347447","latitude":"46.0038153","fips_code":"30093","img_large_path":"fsa/8d08000/8d08400/8d08404v.jpg","img_medium_path":"fsa/8d08000/8d08400/8d08404r.jpg","img_thumb_img":"fsa/8d08000/8d08400/8d08404_150px.jpg"},{"loc_item_link":"owi2001010846/PP","call_number":"LC-USW3-008263","photograph_type":"D","photographer_name":"Russell Lee","caption":"Butte, Montana. Anaconda Copper Mining Company. John Herlihy, shift boss at the mountain con copper mine","year":"1942","month":"9","vanderbilt_level1":"People As Such","vanderbilt_level2":"Groups and Individuals","vanderbilt_level3":"Miners","lot_number":"229","city":"Butte","county":"Silver Bow County","state":"Montana","country":"United States","longitude":"-112.5347447","latitude":"46.0038153","fips_code":"30093","img_large_path":"fsa/8d08000/8d08400/8d08405v.jpg","img_medium_path":"fsa/8d08000/8d08400/8d08405r.jpg","img_thumb_img":"fsa/8d08000/8d08400/8d08405_150px.jpg"},{"loc_item_link":"owi2001010847/PP","call_number":"LC-USW3-008264","photograph_type":"D","photographer_name":"Russell Lee","caption":"Butte, Montana. Anacoda Copper Mining Company. The victory labor-management production committee of the Butte mines meets regularly. In the back row from left to right are: J.A. Livingston, Anacoda Copper Mining Company; E.I. Renouard, assistant general superintendent, ACM; H.J. Rahilly, assistant general superintendent, ACM; Charles Black, Butte miners&#39; union; John Downs, boiler makers&#39; union; W.J. McMahon, commissioner of labor of ACM; John F. Bird, electricians&#39; union; J.P. Ryan, foreman of ACM; Ira Steck, superintendent, electrical department of ACM; James Cusick, machinists&#39; union; John J. Mickelson, Butte miners&#39; union; Eugene Hogan, superintendent ACM. In the front row reading from left to right are: S.S. McGlone, general superintendednt, ACM; Bert Riley, Butte miners&#39; union; Dennis McCarthy, Butte miners&#39; union; A.C. Gibley, ACM; Carl Stenberg, painters&#39; union; John Eathorne, foreman of ACM; John Gaffney, cappenters&#39; union","year":"1942","month":"9","vanderbilt_level1":"Organized Society","vanderbilt_level2":"Labor Organization","vanderbilt_level3":"Meetings, Speakers, Voting","lot_number":"229","city":"Butte","county":"Silver Bow County","state":"Montana","country":"United States","longitude":"-112.5347447","latitude":"46.0038153","fips_code":"30093","img_large_path":"fsa/8d08000/8d08400/8d08406v.jpg","img_medium_path":"fsa/8d08000/8d08400/8d08406r.jpg","img_thumb_img":"fsa/8d08000/8d08400/8d08406_150px.jpg"},{"loc_item_link":"owi2001010849/PP","call_number":"LC-USW3-008266","photograph_type":"D","photographer_name":"Russell Lee","caption":"Butte, Montana. Anaconda Copper Mining Company. Timbers are loaded onto trucks for transporting to the cage which carries them underground to the copper mine","year":"1942","month":"9","vanderbilt_level1":"Work","vanderbilt_level2":"Mining, Oil Wells, Quarrying","vanderbilt_level3":"Copper","lot_number":"229","city":"Butte","county":"Silver Bow County","state":"Montana","country":"United States","longitude":"-112.5347447","latitude":"46.0038153","fips_code":"30093","img_large_path":"fsa/8d08000/8d08400/8d08408v.jpg","img_medium_path":"fsa/8d08000/8d08400/8d08408r.jpg","img_thumb_img":"fsa/8d08000/8d08400/8d08408_150px.jpg"},{"loc_item_link":"owi2001010850/PP","call_number":"LC-USW3-008267","photograph_type":"D","photographer_name":"Russell Lee","caption":"Butte, Montana. Anaconda Copper Mining Company. Yardful of timber to be used in the copper mines","year":"1942","month":"9","vanderbilt_level1":"Work","vanderbilt_level2":"Mining, Oil Wells, Quarrying","vanderbilt_level3":"Copper","lot_number":"229","city":"Butte","county":"Silver Bow County","state":"Montana","country":"United States","longitude":"-112.5347447","latitude":"46.0038153","fips_code":"30093","img_large_path":"fsa/8d08000/8d08400/8d08409v.jpg","img_medium_path":"fsa/8d08000/8d08400/8d08409r.jpg","img_thumb_img":"fsa/8d08000/8d08400/8d08409_150px.jpg"},{"loc_item_link":"owi2001010851/PP","call_number":"LC-USW3-008268","photograph_type":"D","photographer_name":"Russell Lee","caption":"Butte, Montana. Anaconda Copper Mining Company. Yardful of timber to be used in the copper mines","year":"1942","month":"9","vanderbilt_level1":"Work","vanderbilt_level2":"Mining, Oil Wells, Quarrying","vanderbilt_level3":"Copper","lot_number":"229","city":"Butte","county":"Silver Bow County","state":"Montana","country":"United States","longitude":"-112.5347447","latitude":"46.0038153","fips_code":"30093","img_large_path":"fsa/8d08000/8d08400/8d08410v.jpg","img_medium_path":"fsa/8d08000/8d08400/8d08410r.jpg","img_thumb_img":"fsa/8d08000/8d08400/8d08410_150px.jpg"},{"loc_item_link":"owi2001010852/PP","call_number":"LC-USW3-008269","photograph_type":"D","photographer_name":"Russell Lee","caption":"Butte, Montana. Anaconda Copper Mining Company. Machinist measuring diameter of pump plunger which he is making in the machine shop","year":"1942","month":"9","vanderbilt_level1":"Work","vanderbilt_level2":"Processing and Manufacturing","vanderbilt_level3":"Machinery, Hardware, Devices","lot_number":"229","city":"Butte","county":"Silver Bow County","state":"Montana","country":"United States","longitude":"-112.5347447","latitude":"46.0038153","fips_code":"30093","img_large_path":"fsa/8d08000/8d08400/8d08411v.jpg","img_medium_path":"fsa/8d08000/8d08400/8d08411r.jpg","img_thumb_img":"fsa/8d08000/8d08400/8d08411_150px.jpg"},{"loc_item_link":"owi2001010853/PP","call_number":"LC-USW3-008270","photograph_type":"D","photographer_name":"Russell Lee","caption":"Butte, Montana. Anaconda Copper Mining Company. Machinist at a lathe in machine shop","year":"1942","month":"9","vanderbilt_level1":"Work","vanderbilt_level2":"Processing and Manufacturing","vanderbilt_level3":"Machinery, Hardware, Devices","lot_number":"229","city":"Butte","county":"Silver Bow County","state":"Montana","country":"United States","longitude":"-112.5347447","latitude":"46.0038153","fips_code":"30093","img_large_path":"fsa/8d08000/8d08400/8d08412v.jpg","img_medium_path":"fsa/8d08000/8d08400/8d08412r.jpg","img_thumb_img":"fsa/8d08000/8d08400/8d08412_150px.jpg"},{"loc_item_link":"owi2001010855/PP","call_number":"LC-USW3-008272","photograph_type":"D","photographer_name":"Russell Lee","caption":"Gravelly Range, Madison County, Montana. Sheepherder","year":"1942","month":"9","vanderbilt_level1":"People As Such","vanderbilt_level2":"Groups and Individuals","vanderbilt_level3":"Sheep Ranchers","lot_number":"27","city":"Gravelly Range","county":"Madison County","state":"Montana","country":"United States","longitude":"-112.3702981","latitude":"46.8307722","fips_code":"30057","img_large_path":"fsa/8d08000/8d08400/8d08414v.jpg","img_medium_path":"fsa/8d08000/8d08400/8d08414r.jpg","img_thumb_img":"fsa/8d08000/8d08400/8d08414_150px.jpg"},{"loc_item_link":"owi2001010856/PP","call_number":"LC-USW3-008273","photograph_type":"D","photographer_name":"Russell Lee","caption":"Big Hole Valley, Beaverhead County, Montana. Barn on a ranch. This barn was built without blueprints or any drawn plans","year":"1942","month":"9","vanderbilt_level1":"The Land","vanderbilt_level2":"Farms, Lands, Conditions","vanderbilt_level3":"Barns","lot_number":"10","city":"","county":"Beaverhead County","state":"Montana","country":"United States","longitude":"-112.59199","latitude":"44.6383635","fips_code":"30001","img_large_path":"fsa/8d08000/8d08400/8d08415v.jpg","img_medium_path":"fsa/8d08000/8d08400/8d08415r.jpg","img_thumb_img":"fsa/8d08000/8d08400/8d08415_150px.jpg"},{"loc_item_link":"owi2001010857/PP","call_number":"LC-USW3-008274","photograph_type":"D","photographer_name":"Russell Lee","caption":"Gravelly Range, Madison County, Montana. Sheepherder","year":"1942","month":"9","vanderbilt_level1":"People As Such","vanderbilt_level2":"Groups and Individuals","vanderbilt_level3":"Sheep Ranchers","lot_number":"27","city":"Gravelly Range","county":"Madison County","state":"Montana","country":"United States","longitude":"-112.3702981","latitude":"46.8307722","fips_code":"30057","img_large_path":"fsa/8d08000/8d08400/8d08416v.jpg","img_medium_path":"fsa/8d08000/8d08400/8d08416r.jpg","img_thumb_img":"fsa/8d08000/8d08400/8d08416_150px.jpg"},{"loc_item_link":"owi2001010858/PP","call_number":"LC-USW3-008275","photograph_type":"D","photographer_name":"Russell Lee","caption":"Gravelly Range, Madison County, Montana. Sheepherder","year":"1942","month":"9","vanderbilt_level1":"People As Such","vanderbilt_level2":"Groups and Individuals","vanderbilt_level3":"Sheep Ranchers","lot_number":"27","city":"Gravelly Range","county":"Madison County","state":"Montana","country":"United States","longitude":"-112.3702981","latitude":"46.8307722","fips_code":"30057","img_large_path":"fsa/8d08000/8d08400/8d08417v.jpg","img_medium_path":"fsa/8d08000/8d08400/8d08417r.jpg","img_thumb_img":"fsa/8d08000/8d08400/8d08417_150px.jpg"},{"loc_item_link":"owi2001010859/PP","call_number":"LC-USW3-008276","photograph_type":"D","photographer_name":"Russell Lee","caption":"Grasshopper Valley, Beaverhead County, Montana","year":"1942","month":"9","vanderbilt_level1":"The Land","vanderbilt_level2":"General","vanderbilt_level3":"Land","lot_number":"10","city":"Grasshopper Valley","county":"Beaverhead County","state":"Montana","country":"United States","longitude":"-113.0155917","latitude":"45.1679783","fips_code":"30001","img_large_path":"fsa/8d08000/8d08400/8d08418v.jpg","img_medium_path":"fsa/8d08000/8d08400/8d08418r.jpg","img_thumb_img":"fsa/8d08000/8d08400/8d08418_150px.jpg"}]